rangedict.py
rangedict-0.1.7.dist-info/LICENSE
rangedict-0.1.7.dist-info/METADATA
rangedict-0.1.7.dist-info/WHEEL
rangedict-0.1.7.dist-info/top_level.txt
rangedict-0.1.7.dist-info/RECORD
