Metadata-Version: 2.1
Name: rangedict
Version: 0.1.7
Summary: range dict is a dict whose key is a range
Home-page: https://github.com/WKPlus/rangedict.git
Author: WKPlus
Author-email: qifa.zhao@gmail.com
License: MIT
Platform: UNKNOWN
License-File: LICENSE
